gswidgetkit/__init__.py
gswidgetkit/buttons.py
gswidgetkit/checkbox.py
gswidgetkit/color_picker.py
gswidgetkit/constants.py
gswidgetkit/dropdown.py
gswidgetkit/foldpanelbar.py
gswidgetkit/label.py
gswidgetkit/number_field.py
gswidgetkit/panel.py
gswidgetkit/popups.py
gswidgetkit/scrollbar.py
gswidgetkit/textctrl.py
gswidgetkit/tooltip.py
gswidgetkit/utils.py
gswidgetkit/z_matrix.py
gswidgetkit/zoom_panel.py
gswidgetkit/icons/__init__.py
gswidgetkit/icons/icons.py
gswidgetkit-0.3.3.dist-info/LICENSE
gswidgetkit-0.3.3.dist-info/METADATA
gswidgetkit-0.3.3.dist-info/WHEEL
gswidgetkit-0.3.3.dist-info/top_level.txt
gswidgetkit-0.3.3.dist-info/RECORD
