Metadata-Version: 2.1
Name: gswidgetkit
Version: 0.3.3
Summary: Custom widget toolkit for easier creation of customized wxPython GUIs
Home-page: https://github.com/GimelStudio/gswidgetkit
Author: Noah Rahm
Author-email: correctsyntax@yahoo.com
License: Apache 2.0
Keywords: wxpython,widgets,custom
Classifier: Development Status :: 2 - Pre-Alpha
Classifier: Intended Audience :: Developers
Classifier: Operating System :: OS Independent
Classifier: Topic :: Desktop Environment
Classifier: Topic :: Multimedia :: Graphics :: Editors
Classifier: License :: OSI Approved :: Apache Software License
Classifier: Programming Language :: Python :: 3
Classifier: Programming Language :: Python :: 3.8
Classifier: Programming Language :: Python :: 3.9
Classifier: Programming Language :: Python :: 3.10
Classifier: Programming Language :: Python :: 3.11
License-File: LICENSE
Requires-Dist: wxpython ==4.2.1
